dicrivers/__init__.py
dicrivers/dicrivers.py
dicrivers/geo_utils.py
dicrivers-0.0.dist-info/LICENSE
dicrivers-0.0.dist-info/METADATA
dicrivers-0.0.dist-info/WHEEL
dicrivers-0.0.dist-info/top_level.txt
dicrivers-0.0.dist-info/RECORD
