Metadata-Version: 2.1
Name: dicrivers
Version: 0.0
Summary: A package to create bgc river inputs for ocean models
Home-page: https://github.com/raphaeldussin/DICRIVERS
Author: Raphael Dussin
Author-email: raphael.dussin@gmail.com
License: GPLv3
Keywords: ocean forcing
Platform: UNKNOWN
